MANIFEST.in
README.txt
setup.py
vfb2ufo3/__init__.py
vfb2ufo3/core.pyd
vfb2ufo3/fea.pyd
vfb2ufo3/glif.pyd
vfb2ufo3/user.py
vfb2ufo3/vfb.pyd
vfb2ufo3.egg-info/PKG-INFO
vfb2ufo3.egg-info/SOURCES.txt
vfb2ufo3.egg-info/dependency_links.txt
vfb2ufo3.egg-info/top_level.txt