Metadata-Version: 2.1
Name: vfb2ufo3
Version: 0.8.5
Summary: UFO converter for Windows FontLab 5.2
Home-page: https://github.com/spiratype/vfb_ufo3
Author: Jameson R. Spires
Author-email: jameson.spires@gmail.com
License: MIT
Platform: UNKNOWN
Classifier: Development Status :: 4 - Beta
Classifier: Environment :: Other Environment
Classifier: License :: OSI Approved :: MIT License
Classifier: Programming Language :: Python :: 2.7
